pytest_sphinx.py
pytest_sphinx-0.7.1.dist-info/licenses/LICENSE
pytest_sphinx-0.7.1.dist-info/METADATA
pytest_sphinx-0.7.1.dist-info/WHEEL
pytest_sphinx-0.7.1.dist-info/entry_points.txt
pytest_sphinx-0.7.1.dist-info/top_level.txt
pytest_sphinx-0.7.1.dist-info/RECORD
