Metadata-Version: 2.4
Name: pytest-sphinx
Version: 0.7.1
Summary: Doctest plugin for pytest with support for Sphinx-specific doctest-directives
Author-email: Thomas Wimmer <thomaswimmer@posteo.com>
Maintainer-email: Thomas Wimmer <thomaswimmer@posteo.com>
License: 
Project-URL: homepage, https://github.com/thisch/pytest-sphinx
Keywords: sphinx,pytest,rst
Classifier: Development Status :: 4 - Beta
Classifier: Framework :: Pytest
Classifier: Intended Audience :: Developers
Classifier: Topic :: Software Development :: Testing
Classifier: Programming Language :: Python
Classifier: Programming Language :: Python :: 3
Classifier: Programming Language :: Python :: 3.9
Classifier: Programming Language :: Python :: 3.10
Classifier: Programming Language :: Python :: 3.11
Classifier: Programming Language :: Python :: 3.12
Classifier: Programming Language :: Python :: 3.13
Classifier: Programming Language :: Python :: 3.14
Classifier: Programming Language :: Python :: Implementation :: CPython
Classifier: Operating System :: OS Independent
Classifier: License :: OSI Approved :: BSD License
Requires-Python: >=3.10
License-File: LICENSE
Requires-Dist: pytest>=8.1.1
Provides-Extra: lint
Requires-Dist: ruff; extra == "lint"
Dynamic: license-file
